a10sa_script-1.0.2.dist-info/METADATA
a10sa_script-1.0.2.dist-info/WHEEL
a10sa_script-1.0.2.dist-info/entry_points.txt
a10sa_script-1.0.2.dist-info/licenses/LICENSE.rst
a10sa_script/__init__.py
a10sa_script/__main__.py
a10sa_script/command/__init__.py
a10sa_script/command/base.py
a10sa_script/command/vorze.py
a10sa_script/exceptions.py
a10sa_script/player/__init__.py
a10sa_script/player/funscript.py
a10sa_script/player/player.py
a10sa_script/player/vorze.py
a10sa_script/py.typed
a10sa_script/script/__init__.py
a10sa_script/script/base.py
a10sa_script/script/funscript.py
a10sa_script/script/vcsx.py
a10sa_script/script/vorze.py
a10sa_script/utils.py
a10sa_script-1.0.2.dist-info/RECORD
