Metadata-Version: 2.1
Name: a10sa-script
Version: 1.0.2
Summary: A10SA Script
Author-Email: byeonhyeok <bhrevol@gmail.com>
License: MIT
Classifier: Development Status :: 3 - Alpha
Project-URL: Changelog, https://github.com/bhrevol/a10sa-script/releases
Project-URL: homepage, https://github.com/bhrevol/a10sa-script
Project-URL: repository, https://github.com/bhrevol/a10sa-script
Project-URL: documentation, https://a10sa-script.readthedocs.io
Requires-Python: <4.0,>=3.10
Requires-Dist: click>=8.1.8
Requires-Dist: sortedcontainers>=2.4.0
Requires-Dist: loguru>=0.7.3
Requires-Dist: buttplug-py>=0.2.0
Provides-Extra: ble
Requires-Dist: bleak>=0.22.3; python_version < "3.14" and extra == "ble"
